uedition_editor/__about__.py
uedition_editor/__init__.py
uedition_editor/__main__.py
uedition_editor/cron.py
uedition_editor/settings.py
uedition_editor/state.py
uedition_editor/api/__init__.py
uedition_editor/api/auth.py
uedition_editor/api/branches.py
uedition_editor/api/configs.py
uedition_editor/api/files.py
uedition_editor/api/tests.py
uedition_editor/api/util.py
uedition_editor/cli/__init__.py
uedition_editor/frontend/dist/index.html
uedition_editor/frontend/dist/ueditor.svg
uedition_editor/frontend/dist/assets/CodeMirrorEditor-C8CjCBiK.js
uedition_editor/frontend/dist/assets/CodeMirrorEditor-DUGUrxLC.css
uedition_editor/frontend/dist/assets/FolderEditor-CP4gu_Pe.js
uedition_editor/frontend/dist/assets/ImageEditor-DTjQQ12K.js
uedition_editor/frontend/dist/assets/PdfEditor-Z53LWeO4.js
uedition_editor/frontend/dist/assets/TeiEditor-De9iZv7l.js
uedition_editor/frontend/dist/assets/index-B32uewzl.css
uedition_editor/frontend/dist/assets/index-BlcCdQxr.js
uedition_editor/frontend/dist/assets/index-Vcq4gwWv.js
uedition_editor-2.0.1.dist-info/METADATA
uedition_editor-2.0.1.dist-info/WHEEL
uedition_editor-2.0.1.dist-info/entry_points.txt
uedition_editor-2.0.1.dist-info/licenses/LICENSE.txt
uedition_editor-2.0.1.dist-info/RECORD
