Metadata-Version: 2.4
Name: uEdition-Editor
Version: 2.0.1
Project-URL: Documentation, https://github.com/uEdition/uEditor#readme
Project-URL: Issues, https://github.com/uEdition/uEditor/issues
Project-URL: Source, https://github.com/uEdition/uEditor
Author-email: Mark Hall <mark.hall@work.room3b.eu>
License-Expression: MIT
License-File: LICENSE.txt
Classifier: Development Status :: 4 - Beta
Classifier: Programming Language :: Python
Classifier: Programming Language :: Python :: 3.11
Classifier: Programming Language :: Python :: 3.12
Classifier: Programming Language :: Python :: 3.13
Classifier: Programming Language :: Python :: Implementation :: CPython
Classifier: Programming Language :: Python :: Implementation :: PyPy
Requires-Python: >=3.11
Requires-Dist: aiocron<3,>=2.1
Requires-Dist: fastapi<1
Requires-Dist: httptools<1
Requires-Dist: httpx<1,>=0.28.1
Requires-Dist: lxml<7,>=5
Requires-Dist: pydantic-settings<3,>=2
Requires-Dist: pydantic[email]<3,>=2
Requires-Dist: pygit2<2,>=1.17.0
Requires-Dist: pyjwt[crypto]<3,>=2.10.1
Requires-Dist: python-multipart<1,>=0.0.9
Requires-Dist: python-slugify<9,>=8.0.4
Requires-Dist: pyyaml-include<3,>=2
Requires-Dist: pyyaml<7,>=6
Requires-Dist: typer<1,>=0.15.1
Requires-Dist: uedition<2.1,>=2.0.0b5
Requires-Dist: uvicorn<1
Requires-Dist: websockets<17,>=15
